<annotation>
	<folder>image</folder>
	<filename>61.jpg</filename>
	<path>C:\Users\Ryu\Documents\10_tech\10_object_detection\infer\data\image\61.jpg</path>
	<source>
		<database>Unknown</database>
	</source>
	<size>
		<width>1920</width>
		<height>1080</height>
		<depth>3</depth>
	</size>
	<segmented>0</segmented>
	<object>
		<name>person</name>
		<pose>Unspecified</pose>
		<truncated>1</truncated>
		<difficult>0</difficult>
		<bndbox>
			<xmin>701</xmin>
			<ymin>517</ymin>
			<xmax>1067</xmax>
			<ymax>1080</ymax>
		</bndbox>
	</object>
	<object>
		<name>person</name>
		<pose>Unspecified</pose>
		<truncated>1</truncated>
		<difficult>0</difficult>
		<bndbox>
			<xmin>38</xmin>
			<ymin>574</ymin>
			<xmax>320</xmax>
			<ymax>1080</ymax>
		</bndbox>
	</object>
	<object>
		<name>car</name>
		<pose>Unspecified</pose>
		<truncated>0</truncated>
		<difficult>0</difficult>
		<bndbox>
			<xmin>1022</xmin>
			<ymin>661</ymin>
			<xmax>1626</xmax>
			<ymax>829</ymax>
		</bndbox>
	</object>
	<object>
		<name>car</name>
		<pose>Unspecified</pose>
		<truncated>0</truncated>
		<difficult>0</difficult>
		<bndbox>
			<xmin>1215</xmin>
			<ymin>613</ymin>
			<xmax>1584</xmax>
			<ymax>713</ymax>
		</bndbox>
	</object>
	<object>
		<name>traffic light</name>
		<pose>Unspecified</pose>
		<truncated>0</truncated>
		<difficult>0</difficult>
		<bndbox>
			<xmin>1814</xmin>
			<ymin>324</ymin>
			<xmax>1856</xmax>
			<ymax>406</ymax>
		</bndbox>
	</object>
</annotation>
